RobotLog2DB/RobotLog2DB.pdf
RobotLog2DB/__init__.py
RobotLog2DB/__main__.py
RobotLog2DB/robotlog2db.py
RobotLog2DB/version.py
RobotLog2DB/xsd/robot.xsd
robotframework_robotlog2db-1.5.4.dist-info/METADATA
robotframework_robotlog2db-1.5.4.dist-info/WHEEL
robotframework_robotlog2db-1.5.4.dist-info/entry_points.txt
robotframework_robotlog2db-1.5.4.dist-info/top_level.txt
robotframework_robotlog2db-1.5.4.dist-info/RECORD
