Metadata-Version: 2.1
Name: robotframework-robotlog2db
Version: 1.5.4
Summary: Imports robot result(s) to TestResultWebApp database
Home-page: https://github.com/test-fullautomation/robotframework-robotlog2db
Author: Tran Duy Ngoan
Author-email: Ngoan.TranDuy@vn.bosch.com
License: UNKNOWN
Platform: UNKNOWN
Classifier: Programming Language :: Python :: 3
Classifier: License :: OSI Approved :: Apache Software License
Classifier: Operating System :: OS Independent
Classifier: Development Status :: 4 - Beta
Classifier: Intended Audience :: Developers
Classifier: Topic :: Software Development
Requires-Python: >=3.0
Requires-Dist: colorama
Requires-Dist: robotframework
Requires-Dist: lxml
Requires-Dist: TestResultDBAccess
